{
  "indexes": [
    {
      "collectionGroup": "friendRequests",
      "queryScope": "COLLECTION",
      "fields": [
        { "fieldPath": "to",     "order": "ASCENDING" },
        { "fieldPath": "status", "order": "ASCENDING" }
      ]
    },
    {
      "collectionGroup": "friendRequests",
      "queryScope": "COLLECTION",
      "fields": [
        { "fieldPath": "from",   "order": "ASCENDING" },
        { "fieldPath": "status", "order": "ASCENDING" }
      ]
    },
    {
      "collectionGroup": "friendRequests",
      "queryScope": "COLLECTION",
      "fields": [
        { "fieldPath": "from",      "order": "ASCENDING" },
        { "fieldPath": "createdAt", "order": "ASCENDING" }
      ]
    },
    {
      "collectionGroup": "reports",
      "queryScope": "COLLECTION",
      "fields": [
        { "fieldPath": "status",    "order": "ASCENDING"  },
        { "fieldPath": "createdAt", "order": "DESCENDING" }
      ]
    },
    {
      "collectionGroup": "rateLimitStrikes",
      "queryScope": "COLLECTION",
      "fields": [
        { "fieldPath": "at", "order": "DESCENDING" }
      ]
    },
    {
      "collectionGroup": "messages",
      "queryScope": "COLLECTION_GROUP",
      "fields": [
        { "fieldPath": "sender",    "order": "ASCENDING" },
        { "fieldPath": "createdAt", "order": "ASCENDING" }
      ]
    }
  ],
  "fieldOverrides": []
}
